odoo/addons/l10n_br_sale_invoice_plan/README.rst
odoo/addons/l10n_br_sale_invoice_plan/__init__.py
odoo/addons/l10n_br_sale_invoice_plan/__manifest__.py
odoo/addons/l10n_br_sale_invoice_plan/demo/sale_order_demo.xml
odoo/addons/l10n_br_sale_invoice_plan/i18n/l10n_br_sale_invoice_plan.pot
odoo/addons/l10n_br_sale_invoice_plan/i18n/pt_BR.po
odoo/addons/l10n_br_sale_invoice_plan/models/__init__.py
odoo/addons/l10n_br_sale_invoice_plan/models/sale_invoice_plan.py
odoo/addons/l10n_br_sale_invoice_plan/readme/CONFIGURE.md
odoo/addons/l10n_br_sale_invoice_plan/readme/CONTRIBUTORS.md
odoo/addons/l10n_br_sale_invoice_plan/readme/CREDITS.md
odoo/addons/l10n_br_sale_invoice_plan/readme/DESCRIPTION.md
odoo/addons/l10n_br_sale_invoice_plan/readme/INSTALL.md
odoo/addons/l10n_br_sale_invoice_plan/static/description/icon.png
odoo/addons/l10n_br_sale_invoice_plan/static/description/index.html
odoo/addons/l10n_br_sale_invoice_plan/tests/__init__.py
odoo/addons/l10n_br_sale_invoice_plan/tests/test_l10n_br_sale_invoice_plan.py
odoo_addon_l10n_br_sale_invoice_plan-16.0.3.0.0.dist-info/METADATA
odoo_addon_l10n_br_sale_invoice_plan-16.0.3.0.0.dist-info/WHEEL
odoo_addon_l10n_br_sale_invoice_plan-16.0.3.0.0.dist-info/top_level.txt
odoo_addon_l10n_br_sale_invoice_plan-16.0.3.0.0.dist-info/RECORD
